onnx_connx/__init__.py
onnx_connx/__main__.py
onnx_connx/backend.py
onnx_connx/backend_rep.py
onnx_connx/compiler.py
onnx_connx/proto.py
onnx_connx/test_connx_backend.py
onnx_connx/opset/BatchNormalization.py
onnx_connx/opset/Cast.py
onnx_connx/opset/Conv.py
onnx_connx/opset/GlobalAveragePool.py
onnx_connx/opset/MaxPool.py
onnx_connx/opset/Resize.py
onnx_connx/opset/__init__.py
onnx_connx/opset/opset.py
onnx_connx/opset/util.py
tests/__init__.py
onnx_connx_neowine-0.1.4.dist-info/LICENSE
onnx_connx_neowine-0.1.4.dist-info/METADATA
onnx_connx_neowine-0.1.4.dist-info/WHEEL
onnx_connx_neowine-0.1.4.dist-info/entry_points.txt
onnx_connx_neowine-0.1.4.dist-info/top_level.txt
onnx_connx_neowine-0.1.4.dist-info/RECORD
