Metadata-Version: 2.1
Name: onnx-connx-neowine
Version: 0.1.4
Summary: ONNX to CONNX converting tool
Home-page: https://github.com/semihlab/onnx-connx
Author: Chanjin Park
Author-email: chans@neowine.com
License: UNKNOWN
Project-URL: Bug Tracker, https://github.com/semihlab/onnx-connx/issues
Platform: UNKNOWN
Classifier: Environment :: Console
Classifier: License :: OSI Approved :: GNU Lesser General Public License v3 (LGPLv3)
Classifier: Topic :: Software Development :: Build Tools
